bluescope/__init__.py
bluescope/logger.py
bluescope/profiler.py
bluescope/statsutils.py
bluescope/db/__init__.py
bluescope/db/base.py
bluescope/db/consts.py
bluescope/db/redshift.py
BlueScope-1.0.0a2.dist-info/LICENSE
BlueScope-1.0.0a2.dist-info/METADATA
BlueScope-1.0.0a2.dist-info/WHEEL
BlueScope-1.0.0a2.dist-info/top_level.txt
BlueScope-1.0.0a2.dist-info/RECORD
