Metadata-Version: 2.1
Name: BlueScope
Version: 1.0.0a2
Summary: Library to profile and compare SQL queries for different databases.
Home-page: https://github.com/Arkady-A/BlueScope
Author: ArkadyA
Author-email: mirzabekian.arkadii@gmail.com
Classifier: Programming Language :: Python :: 3
Classifier: License :: OSI Approved :: GNU General Public License v3 (GPLv3)
Classifier: Operating System :: OS Independent
Requires-Python: >=3.9
License-File: LICENSE
Requires-Dist: redshift-connector ==2.0.918
Requires-Dist: setuptools ==69.0.3
Requires-Dist: colorlog ==6.8.2
Requires-Dist: scipy ==1.12.0
